.DS_Store
my_module/__init__.py
my_module/my_function.py
my_module/scraping.py
phdAncientHistGrkPap-0.2.0.dist-info/METADATA
phdAncientHistGrkPap-0.2.0.dist-info/WHEEL
phdAncientHistGrkPap-0.2.0.dist-info/top_level.txt
phdAncientHistGrkPap-0.2.0.dist-info/RECORD
