Metadata-Version: 2.1
Name: phdAncientHistGrkPap
Version: 0.2.0
Requires-Dist: pandas
Requires-Dist: requests
Requires-Dist: beautifulsoup4
